ibex_non_ca_helpers/__init__.py
ibex_non_ca_helpers/compress_hex.py
ibex_non_ca_helpers/macros.py
ibex_non_ca_helpers/pv.py
ibex_non_ca_helpers/version.py
ibex_non_ca_helpers-0.1.0.dist-info/licenses/LICENSE
ibex_non_ca_helpers-0.1.0.dist-info/METADATA
ibex_non_ca_helpers-0.1.0.dist-info/WHEEL
ibex_non_ca_helpers-0.1.0.dist-info/top_level.txt
ibex_non_ca_helpers-0.1.0.dist-info/RECORD
