Metadata-Version: 2.4
Name: ibex-non-ca-helpers
Version: 0.1.0
Summary: Python helpers for IBEX which do not rely on channel access
Author-email: ISIS Experiment Controls <ISISExperimentControls@stfc.ac.uk>
Maintainer-email: ISIS Experiment Controls <ISISExperimentControls@stfc.ac.uk>
Project-URL: Homepage, https://github.com/isiscomputinggroup/ibex-non-ca-helpers
Project-URL: Bug Reports, https://github.com/isiscomputinggroup/ibex-non-ca-helpers/issues
Project-URL: Source, https://github.com/isiscomputinggroup/ibex-non-ca-helpers
Requires-Python: >=3.11
License-File: LICENSE
Provides-Extra: dev
Requires-Dist: ruff; extra == "dev"
Requires-Dist: pytest; extra == "dev"
Requires-Dist: pyright; extra == "dev"
Requires-Dist: pytest-cov; extra == "dev"
Dynamic: license-file
